tdcsm/__init__.py
tdcsm/cli.py
tdcsm/config.yaml
tdcsm/dbutil.py
tdcsm/logging.py
tdcsm/model.py
tdcsm/pic_TDCOA_Banner.gif
tdcsm/pic_TDCOAdot.gif
tdcsm/pic_TDCOAdot2.gif
tdcsm/pptx.py
tdcsm/run_cmdline
tdcsm/run_cmdline.py
tdcsm/run_gui
tdcsm/run_gui.py
tdcsm/secrets.yaml
tdcsm/source_systems.yaml
tdcsm/tdcoa.py
tdcsm/tdgui.py
tdcsm/tdviz.py
tdcsm/utils.py
tdcsm-0.4.1.6.dist-info/LICENSE
tdcsm-0.4.1.6.dist-info/METADATA
tdcsm-0.4.1.6.dist-info/WHEEL
tdcsm-0.4.1.6.dist-info/entry_points.txt
tdcsm-0.4.1.6.dist-info/top_level.txt
tdcsm-0.4.1.6.dist-info/RECORD
