Metadata-Version: 2.1
Name: tdcsm
Version: 0.4.1.6
Summary: Teradata tools for CSMs (deprecated)
Home-page: https://github.com/tdcoa/tdcsm
Author: Stephen Hilton
Author-email: Stephen@FamilyHilton.com
License: UNKNOWN
Platform: UNKNOWN
Classifier: Programming Language :: Python :: 3
Classifier: License :: OSI Approved :: MIT License
Classifier: Operating System :: OS Independent
Requires-Python: >=3.8
Requires-Dist: pandas
Requires-Dist: numpy
Requires-Dist: requests
Requires-Dist: pyyaml
Requires-Dist: teradatasql
Requires-Dist: matplotlib
Requires-Dist: seaborn
Requires-Dist: python-pptx
Requires-Dist: pydantic
Requires-Dist: sklearn
Requires-Dist: Pillow
Requires-Dist: tk
